README.md
setup.cfg
setup.py
gym_nats/__init__.py
gym_nats/utils.py
gym_nats.egg-info/PKG-INFO
gym_nats.egg-info/SOURCES.txt
gym_nats.egg-info/dependency_links.txt
gym_nats.egg-info/requires.txt
gym_nats.egg-info/top_level.txt